electrumsv_node/__init__.py
electrumsv_node/bitcoin.conf
electrumsv_node/electrumsv_node.py
electrumsv_node/bin/bitcoin-cli.exe
electrumsv_node/bin/bitcoin-miner.exe
electrumsv_node/bin/bitcoin-tx.exe
electrumsv_node/bin/bitcoin-tx.exp
electrumsv_node/bin/bitcoin-tx.lib
electrumsv_node/bin/bitcoinconsensus.lib
electrumsv_node/bin/bitcoind.exe
electrumsv_node/bin/bitcoind.exp
electrumsv_node/bin/bitcoind.lib
electrumsv_node/bin/common.lib
electrumsv_node/bin/rpcclient.lib
electrumsv_node/bin/server.lib
electrumsv_node/bin/util.lib
electrumsv_node/data/README.md
electrumsv_node-1.0.2.dist-info/LICENSE.txt
electrumsv_node-1.0.2.dist-info/METADATA
electrumsv_node-1.0.2.dist-info/WHEEL
electrumsv_node-1.0.2.dist-info/top_level.txt
electrumsv_node-1.0.2.dist-info/RECORD
