Metadata-Version: 2.1
Name: electrumsv-node
Version: 1.0.2
Summary: ElectrumSV RegTest node
Home-page: https://github.com/electrumsv/electrumsv-node
Author: AustEcon
Author-email: AustEcon0922@gmail.com
Maintainer: AustEcon
Maintainer-email: AustEcon0922@gmail.com
License: MIT
Download-URL: https://github.com/electrumsv/electrumsv-node/tarball/1.0.2
Keywords: bitcoinsv,bsv,bitcoin sv,cryptocurrency,tools,wallet
Platform: UNKNOWN
Classifier: Development Status :: 4 - Beta
Classifier: Intended Audience :: Developers
Classifier: Intended Audience :: End Users/Desktop
Classifier: License :: OSI Approved :: MIT License
Classifier: Natural Language :: English
Classifier: Operating System :: OS Independent
Classifier: Programming Language :: Python :: 3.7
Classifier: Programming Language :: Python :: 3.8
Classifier: Programming Language :: Python :: Implementation :: CPython
